fc/__init__.py
fc/auth/__init__.py
fc/auth/auth.py
fc/auth/combo.py
fc/auth/envvarauth.py
fc/auth/fileauth.py
fc/auth/keyboardauth.py
fc/cli/__init__.py
fc/cli/backlog.py
fc/cli/cli_library.py
fc/cli/comment.py
fc/cli/el.py
fc/cli/main.py
fc/cli/task.py
fc/cli/triage.py
fc/cli/version.py
fc/exceptions/__init__.py
fc/exceptions/task_exception.py
fc/jira/__init__.py
fc/jira/backlog_issue.py
fc/jira/backlog_story.py
fc/jira/backlog_task.py
fc/jira/el_task.py
fc/jira/fcissue.py
fc/jira/issue.py
fc/jira/tasks.py
fc/jira/triage_task.py
fcli-4.0.0.dist-info/LICENSE
fcli-4.0.0.dist-info/METADATA
fcli-4.0.0.dist-info/WHEEL
fcli-4.0.0.dist-info/entry_points.txt
fcli-4.0.0.dist-info/top_level.txt
fcli-4.0.0.dist-info/RECORD
