Metadata-Version: 2.1
Name: fcli
Version: 4.0.0
Summary: Helps spread the AwesomeSauce of the Foundational Components team a bit further
Home-page: https://github.com/halprin/fcli
Author: halprin
Author-email: me@halprin.io
License: UNKNOWN
Platform: UNKNOWN
Classifier: Programming Language :: Python :: 3
Classifier: License :: OSI Approved :: GNU General Public License v3 (GPLv3)
Classifier: Operating System :: OS Independent
Requires-Dist: click
Requires-Dist: requests
Requires-Dist: click-datetime
